extrator_xml_fiscal/__init__.py
extrator_xml_fiscal/extrator_base.py
extrator_xml_fiscal/extrator_cancelamento.py
extrator_xml_fiscal/extrator_carta_correcao.py
extrator_xml_fiscal/extrator_cte.py
extrator_xml_fiscal/extrator_evento_base.py
extrator_xml_fiscal/extrator_nfe.py
extrator_xml_fiscal/utils.py
extrator_xml_fiscal-1.0.1.dist-info/LICENSE
extrator_xml_fiscal-1.0.1.dist-info/METADATA
extrator_xml_fiscal-1.0.1.dist-info/WHEEL
extrator_xml_fiscal-1.0.1.dist-info/RECORD
