Metadata-Version: 2.1
Name: extrator-xml-fiscal
Version: 1.0.1
Summary: Biblioteca para extrair dados de documentos fiscais XML
Home-page: https://github.com/luizelias8/extrator-xml-fiscal
License: MIT
Keywords: nfe,xml,fiscal,brasil,sefaz
Author: luizelias8
Author-email: luizelias8@gmail.com
Requires-Python: >=3.13,<4.0
Classifier: Development Status :: 4 - Beta
Classifier: Intended Audience :: Developers
Classifier: License :: OSI Approved :: MIT License
Classifier: Programming Language :: Python :: 3
Classifier: Programming Language :: Python :: 3.13
Classifier: Programming Language :: Python :: 3.10
Classifier: Programming Language :: Python :: 3.11
Classifier: Programming Language :: Python :: 3.8
Classifier: Programming Language :: Python :: 3.9
Classifier: Topic :: Office/Business :: Financial
Classifier: Topic :: Text Processing :: Markup :: XML
Requires-Dist: xmltodict (>=1.0.2,<2.0.0)
Project-URL: Repository, https://github.com/luizelias8/extrator-xml-fiscal
